pyxu_finufft/__init__.py
pyxu_finufft/operator/__init__.py
pyxu_finufft/operator/linop/__init__.py
pyxu_finufft/operator/linop/nufft.py
pyxu_finufft-1.0.1.dist-info/METADATA
pyxu_finufft-1.0.1.dist-info/WHEEL
pyxu_finufft-1.0.1.dist-info/entry_points.txt
pyxu_finufft-1.0.1.dist-info/licenses/LICENSE
pyxu_finufft-1.0.1.dist-info/RECORD
