Metadata-Version: 2.3
Name: pyxu_finufft
Version: 1.0.1
Summary: Pyxu bindings to the Flatiron Institute Non-uniform Fast Fourier Transform (FINUFFT) library.
Project-URL: download, https://github.com/pyxu-org/pyxu_finufft
Author-email: "S. Kashani" <sepand@kashani.ch>
License-Expression: MIT
License-File: LICENSE
Classifier: Development Status :: 4 - Beta
Classifier: Framework :: Pycsou
Classifier: Intended Audience :: Science/Research
Classifier: License :: OSI Approved :: MIT License
Classifier: Programming Language :: Python :: 3.10
Classifier: Programming Language :: Python :: 3.11
Classifier: Programming Language :: Python :: 3.12
Classifier: Programming Language :: Python :: Implementation :: CPython
Classifier: Topic :: Scientific/Engineering
Requires-Python: <3.13,>=3.10
Requires-Dist: finufft<3,>=2.2.0
Requires-Dist: pyxu
Provides-Extra: all
Requires-Dist: pyxu-finufft[gpu]; extra == 'all'
Provides-Extra: dev
Requires-Dist: pyxu[dev]; extra == 'dev'
Provides-Extra: gpu
Requires-Dist: cufinufft<3,>=2.2.0; extra == 'gpu'
